Metadata-Version: 2.1
Name: brainscore-core
Version: 2.3.2
License: 
Requires-Python: >=3.11
License-File: LICENSE
Requires-Dist: tqdm
Requires-Dist: numpy<2.0,>=1.21
Requires-Dist: boto3
Requires-Dist: netCDF4
Requires-Dist: xarray<2022.6
Requires-Dist: pandas
Requires-Dist: Pillow
Requires-Dist: psycopg2-binary
Requires-Dist: fire
Requires-Dist: peewee
Requires-Dist: pybtex
Requires-Dist: requests
Provides-Extra: test
Requires-Dist: imageio; extra == "test"
Requires-Dist: moto; extra == "test"
Requires-Dist: pytest; extra == "test"
Requires-Dist: pytest-check; extra == "test"
Requires-Dist: pytest-mock; extra == "test"
Requires-Dist: requests-mock; extra == "test"
